{
  "Name": "Cos its a hedron",
  "ShapeType": "Uniform",
  "PolyTypeCategory": "All",
  "PolyType": "Icosahedron",
  "JohnsonPolyType": "Rotunda",
  "OtherPolyType": "L1",
  "GridType": "Square",
  "GridShape": "Plane",
  "BypassOps": false,
  "SafeLimits": false,
  "PrismP": 5,
  "PrismQ": 2,
  "AppearancePresetName": "Rich",
  "Ops": [
    {
      "OpType": "OppositeLace",
      "FaceSelections": "All",
      "Amount": 0.4,
      "AnimatedAmount": 0.0,
      "Randomize": false,
      "Disabled": false,
      "Animate": false,
      "AnimationRate": 0.0,
      "AnimationAmount": 0.0,
      "AudioLowAmount": 0.0,
      "AudioMidAmount": 0.0,
      "AudioHighAmount": 0.0
    },
    {
      "OpType": "Medial",
      "FaceSelections": "All",
      "Amount": 2.0,
      "AnimatedAmount": 0.0,
      "Randomize": false,
      "Disabled": false,
      "Animate": false,
      "AnimationRate": 0.0,
      "AnimationAmount": 0.0,
      "AudioLowAmount": 0.0,
      "AudioMidAmount": 0.0,
      "AudioHighAmount": 0.0
    },
    {
      "OpType": "Dual",
      "FaceSelections": "All",
      "Amount": 0.06,
      "AnimatedAmount": 0.0,
      "Randomize": false,
      "Disabled": true,
      "Animate": false,
      "AnimationRate": 0.0,
      "AnimationAmount": 0.0,
      "AudioLowAmount": 0.0,
      "AudioMidAmount": 0.0,
      "AudioHighAmount": 0.0
    }
  ]
}