{
  "Name": "The King in Yellow",
  "ShapeType": "Johnson",
  "PolyTypeCategory": "All",
  "PolyType": "Truncated_Octahedron",
  "JohnsonPolyType": "Cupola",
  "OtherPolyType": "UvSphere",
  "GridType": "U_4_6_12",
  "GridShape": "Plane",
  "BypassOps": true,
  "SafeLimits": true,
  "PrismP": 5,
  "PrismQ": 5,
  "AppearancePresetName": "Volumetric",
  "Ops": [
    {
      "OpType": "Loft",
      "FaceSelections": "FacingUp",
      "Amount": 0.3,
      "Amount2": 0.2,
      "AnimatedAmount": 0.0,
      "Randomize": false,
      "Disabled": false,
      "Animate": false,
      "AnimationRate": 0.0,
      "AnimationAmount": 0.0,
      "AudioLowAmount": 0.0,
      "AudioMidAmount": 0.0,
      "AudioHighAmount": 0.0,
      "Tags": null
    },
    {
      "OpType": "VertexRotate",
      "FaceSelections": "Existing",
      "Amount": 0.0,
      "Amount2": 0.0,
      "AnimatedAmount": -0.19,
      "Randomize": false,
      "Disabled": false,
      "Animate": true,
      "AnimationRate": 1.0,
      "AnimationAmount": 0.2,
      "AudioLowAmount": 0.0,
      "AudioMidAmount": 0.0,
      "AudioHighAmount": 0.0,
      "Tags": null
    },
    {
      "OpType": "Loft",
      "FaceSelections": "Existing",
      "Amount": 0.4,
      "Amount2": 0.2,
      "AnimatedAmount": 0.0,
      "Randomize": false,
      "Disabled": false,
      "Animate": false,
      "AnimationRate": 0.0,
      "AnimationAmount": 0.0,
      "AudioLowAmount": 0.0,
      "AudioMidAmount": 0.0,
      "AudioHighAmount": 0.0,
      "Tags": null
    },
    {
      "OpType": "VertexRotate",
      "FaceSelections": "Existing",
      "Amount": 0.0,
      "Amount2": 0.0,
      "AnimatedAmount": 0.12,
      "Randomize": false,
      "Disabled": false,
      "Animate": true,
      "AnimationRate": 2.0,
      "AnimationAmount": 0.2,
      "AudioLowAmount": 0.0,
      "AudioMidAmount": 0.0,
      "AudioHighAmount": 0.0,
      "Tags": null
    },
    {
      "OpType": "Loft",
      "FaceSelections": "Existing",
      "Amount": 0.5,
      "Amount2": 0.2,
      "AnimatedAmount": 0.0,
      "Randomize": false,
      "Disabled": false,
      "Animate": false,
      "AnimationRate": 0.0,
      "AnimationAmount": 0.0,
      "AudioLowAmount": 0.0,
      "AudioMidAmount": 0.0,
      "AudioHighAmount": 0.0,
      "Tags": null
    },
    {
      "OpType": "VertexRotate",
      "FaceSelections": "Existing",
      "Amount": 0.0,
      "Amount2": 0.0,
      "AnimatedAmount": 0.14,
      "Randomize": false,
      "Disabled": false,
      "Animate": true,
      "AnimationRate": 3.0,
      "AnimationAmount": 0.2,
      "AudioLowAmount": 0.0,
      "AudioMidAmount": 0.0,
      "AudioHighAmount": 0.0,
      "Tags": null
    },
    {
      "OpType": "Loft",
      "FaceSelections": "Existing",
      "Amount": 0.6,
      "Amount2": 0.2,
      "AnimatedAmount": 0.0,
      "Randomize": false,
      "Disabled": false,
      "Animate": false,
      "AnimationRate": 0.0,
      "AnimationAmount": 0.0,
      "AudioLowAmount": 0.0,
      "AudioMidAmount": 0.0,
      "AudioHighAmount": 0.0,
      "Tags": null
    }
  ]
}