	{"Name": "foo4", "PolyType":2,"BypassConway":false,"TwoSided":true,"ConwayOperators":[{"op":2,"amount":0.18000000715255738,"disabled":false},{"op":1,"amount":-0.9399999976158142,"disabled":false},{"op":2,"amount":-0.23000000417232514,"disabled":false},{"op":9,"amount":0.0,"disabled":true}],"OffsetAmount":0.0,"RibbonAmount":0.0,"ExtrudeAmount":0.0,"vertexGizmos":false,"faceCenterGizmos":false,"edgeGizmos":false,"faceGizmos":false,"faceGizmosList":[0,2],"dualGizmo":false,"gizmoPallette":[{"r":1.0,"g":0.0,"b":0.0,"a":1.0},{"r":1.0,"g":0.9215686321258545,"b":0.01568627543747425,"a":1.0},{"r":0.0,"g":1.0,"b":0.0,"a":1.0},{"r":0.0,"g":1.0,"b":1.0,"a":1.0},{"r":0.0,"g":0.0,"b":1.0,"a":1.0},{"r":1.0,"g":0.0,"b":1.0,"a":1.0}]}
